<?xml version="1.0" encoding="UTF-8"?><record_update table="sc_cat_item_catalog">
    <sc_cat_item_catalog action="INSERT_OR_UPDATE">
        <sc_cat_item display_value="Loaner Request">1537cf850d0003107f448a43eaab0cde</sc_cat_item>
        <sc_catalog display_value="Service Catalog">e0d08b13c3330100c8b837659bba8fb4</sc_catalog>
        <sys_class_name>sc_cat_item_catalog</sys_class_name>
        <sys_created_by>admin</sys_created_by>
        <sys_created_on>2026-04-03 06:16:34</sys_created_on>
        <sys_id>1d37cf850d0003107f448a43eaab0ce0</sys_id>
        <sys_mod_count>0</sys_mod_count>
        <sys_name>Service Catalog.Loaner Request</sys_name>
        <sys_package display_value="Loaner Request" source="x_cdltd_loaner_r_0">54e347ac153332107f447e2f9c688219</sys_package>
        <sys_policy/>
        <sys_scope display_value="Loaner Request">54e347ac153332107f447e2f9c688219</sys_scope>
        <sys_update_name>sc_cat_item_catalog_1d37cf850d0003107f448a43eaab0ce0</sys_update_name>
        <sys_updated_by>admin</sys_updated_by>
        <sys_updated_on>2026-04-03 06:16:34</sys_updated_on>
    </sc_cat_item_catalog>
</record_update>
